[
	{"date":"19/08/2017","term":"00009","ketqua":["07","11","13","15","26","51","36"],"jackpot":["07","11","13","15","26","51"],"magicnum":"36"},
	{"date":"16/09/2017","term":"00021","ketqua":["09","12","21","26","29","52","24"],"jackpot":["09","12","21","26","29","52"],"magicnum":"24"},
	{"date":"17/10/2017","term":"00034","ketqua":["01","26","36","40","50","54","31"],"jackpot":["01","26","36","40","50","54"],"magicnum":"31"},
	{"date":"11/11/2017","term":"00045","ketqua":["12","26","33","35","36","44","01"],"jackpot":["12","26","33","35","36","44"],"magicnum":"01"},
	{"date":"18/11/2017","term":"00048","ketqua":["11","12","26","42","50","54","17"],"jackpot":["11","12","26","42","50","54"],"magicnum":"17"},
	{"date":"30/11/2017","term":"00053","ketqua":["05","13","26","37","53","55","28"],"jackpot":["05","13","26","37","53","55"],"magicnum":"28"},
	{"date":"07/12/2017","term":"00056","ketqua":["03","14","26","35","44","54","25"],"jackpot":["03","14","26","35","44","54"],"magicnum":"25"},
	{"date":"26/12/2017","term":"00064","ketqua":["07","11","13","18","26","42","49"],"jackpot":["07","11","13","18","26","42"],"magicnum":"49"},
	{"date":"28/12/2017","term":"00065","ketqua":["07","18","26","29","31","35","34"],"jackpot":["07","18","26","29","31","35"],"magicnum":"34"},
	{"date":"13/01/2018","term":"00072","ketqua":["03","21","25","26","51","55","37"],"jackpot":["03","21","25","26","51","55"],"magicnum":"37"},
	{"date":"27/01/2018","term":"00078","ketqua":["21","26","36","38","40","50","11"],"jackpot":["21","26","36","38","40","50"],"magicnum":"11"},
	{"date":"13/02/2018","term":"00085","ketqua":["09","25","26","30","42","54","19"],"jackpot":["09","25","26","30","42","54"],"magicnum":"19"},
	{"date":"31/03/2018","term":"00104","ketqua":["03","07","31","43","51","53","26"],"jackpot":["03","07","31","43","51","53"],"magicnum":"26"},
	{"date":"14/04/2018","term":"00110","ketqua":["02","10","14","26","45","54","20"],"jackpot":["02","10","14","26","45","54"],"magicnum":"20"},
	{"date":"17/04/2018","term":"00111","ketqua":["02","10","26","27","31","38","39"],"jackpot":["02","10","26","27","31","38"],"magicnum":"39"},
	{"date":"26/04/2018","term":"00115","ketqua":["23","26","29","31","36","54","55"],"jackpot":["23","26","29","31","36","54"],"magicnum":"55"},
	{"date":"12/05/2018","term":"00122","ketqua":["01","09","26","38","54","55","51"],"jackpot":["01","09","26","38","54","55"],"magicnum":"51"},
	{"date":"24/05/2018","term":"00127","ketqua":["24","25","26","29","36","48","40"],"jackpot":["24","25","26","29","36","48"],"magicnum":"40"},
	{"date":"29/05/2018","term":"00129","ketqua":["09","13","17","18","46","50","26"],"jackpot":["09","13","17","18","46","50"],"magicnum":"26"},
	{"date":"31/05/2018","term":"00130","ketqua":["03","15","18","25","26","29","19"],"jackpot":["03","15","18","25","26","29"],"magicnum":"19"},
	{"date":"05/06/2018","term":"00132","ketqua":["11","21","26","32","51","52","05"],"jackpot":["11","21","26","32","51","52"],"magicnum":"05"},
	{"date":"07/06/2018","term":"00133","ketqua":["11","16","18","26","46","47","42"],"jackpot":["11","16","18","26","46","47"],"magicnum":"42"},
	{"date":"18/12/2018","term":"00216","ketqua":["01","09","15","17","25","26","08"],"jackpot":["01","09","15","17","25","26"],"magicnum":"08"},
	{"date":"13/09/2018","term":"00175","ketqua":["04","06","07","26","40","44","09"],"jackpot":["04","06","07","26","40","44"],"magicnum":"09"},
	{"date":"13/11/2018","term":"00201","ketqua":["03","25","26","32","41","47","05"],"jackpot":["03","25","26","32","41","47"],"magicnum":"05"},
	{"date":"17/11/2018","term":"00203","ketqua":["12","22","26","29","45","47","15"],"jackpot":["12","22","26","29","45","47"],"magicnum":"15"},
	{"date":"12/01/2019","term":"00227","ketqua":["07","13","14","26","42","54","11"],"jackpot":["07","13","14","26","42","54"],"magicnum":"11"},
	{"date":"29/01/2019","term":"00234","ketqua":["15","20","26","41","45","55","10"],"jackpot":["15","20","26","41","45","55"],"magicnum":"10"},
	{"date":"14/02/2019","term":"00240","ketqua":["08","15","26","41","43","53","46"],"jackpot":["08","15","26","41","43","53"],"magicnum":"46"},
	{"date":"05/03/2019","term":"00248","ketqua":["01","15","23","51","53","55","26"],"jackpot":["01","15","23","51","53","55"],"magicnum":"26"},
	{"date":"12/03/2019","term":"00251","ketqua":["09","16","26","34","44","49","19"],"jackpot":["09","16","26","34","44","49"],"magicnum":"19"},
	{"date":"02/04/2019","term":"00260","ketqua":["01","04","09","20","22","26","48"],"jackpot":["01","04","09","20","22","26"],"magicnum":"48"},
	{"date":"04/04/2019","term":"00261","ketqua":["16","26","29","38","47","51","13"],"jackpot":["16","26","29","38","47","51"],"magicnum":"13"},
	{"date":"18/04/2019","term":"00267","ketqua":["07","08","15","24","26","48","10"],"jackpot":["07","08","15","24","26","48"],"magicnum":"10"},
	{"date":"27/04/2019","term":"00271","ketqua":["01","11","22","26","33","51","04"],"jackpot":["01","11","22","26","33","51"],"magicnum":"04"},
	{"date":"04/05/2019","term":"00274","ketqua":["01","02","03","17","26","53","50"],"jackpot":["01","02","03","17","26","53"],"magicnum":"50"},
	{"date":"11/05/2019","term":"00277","ketqua":["06","11","20","22","26","28","36"],"jackpot":["06","11","20","22","26","28"],"magicnum":"36"},
	{"date":"04/06/2019","term":"00287","ketqua":["18","20","24","26","33","41","55"],"jackpot":["18","20","24","26","33","41"],"magicnum":"55"},
	{"date":"11/07/2019","term":"00303","ketqua":["06","09","15","26","35","38","34"],"jackpot":["06","09","15","26","35","38"],"magicnum":"34"},
	{"date":"01/08/2019","term":"00312","ketqua":["01","18","39","45","48","49","26"],"jackpot":["01","18","39","45","48","49"],"magicnum":"26"},
	{"date":"03/08/2019","term":"00313","ketqua":["13","24","25","26","27","30","04"],"jackpot":["13","24","25","26","27","30"],"magicnum":"04"},
	{"date":"06/08/2019","term":"00314","ketqua":["09","11","19","20","26","42","17"],"jackpot":["09","11","19","20","26","42"],"magicnum":"17"},
	{"date":"17/08/2019","term":"00319","ketqua":["09","11","24","26","38","53","41"],"jackpot":["09","11","24","26","38","53"],"magicnum":"41"},
	{"date":"17/09/2019","term":"00332","ketqua":["03","14","26","38","43","47","10"],"jackpot":["03","14","26","38","43","47"],"magicnum":"10"},
	{"date":"03/10/2019","term":"00339","ketqua":["04","07","08","26","37","44","29"],"jackpot":["04","07","08","26","37","44"],"magicnum":"29"},
	{"date":"19/10/2019","term":"00346","ketqua":["01","10","21","26","42","43","25"],"jackpot":["01","10","21","26","42","43"],"magicnum":"25"},
	{"date":"22/10/2019","term":"00347","ketqua":["02","16","26","27","36","40","31"],"jackpot":["02","16","26","27","36","40"],"magicnum":"31"},
	{"date":"28/11/2019","term":"00363","ketqua":["01","18","26","28","53","55","14"],"jackpot":["01","18","26","28","53","55"],"magicnum":"14"},
	{"date":"10/12/2019","term":"00368","ketqua":["05","20","33","42","43","49","26"],"jackpot":["05","20","33","42","43","49"],"magicnum":"26"},
	{"date":"14/12/2019","term":"00370","ketqua":["03","30","33","34","40","47","26"],"jackpot":["03","30","33","34","40","47"],"magicnum":"26"},
	{"date":"26/12/2019","term":"00375","ketqua":["05","06","12","18","23","54","26"],"jackpot":["05","06","12","18","23","54"],"magicnum":"26"},
	{"date":"28/12/2019","term":"00376","ketqua":["10","17","26","28","29","32","21"],"jackpot":["10","17","26","28","29","32"],"magicnum":"21"},
	{"date":"31/12/2019","term":"00377","ketqua":["02","22","26","28","44","55","27"],"jackpot":["02","22","26","28","44","55"],"magicnum":"27"},
	{"date":"02/01/2020","term":"00378","ketqua":["12","14","26","29","33","40","50"],"jackpot":["12","14","26","29","33","40"],"magicnum":"50"},
	{"date":"04/01/2020","term":"00379","ketqua":["04","14","26","42","44","55","48"],"jackpot":["04","14","26","42","44","55"],"magicnum":"48"},
	{"date":"16/01/2020","term":"00384","ketqua":["10","11","26","33","44","46","55"],"jackpot":["10","11","26","33","44","46"],"magicnum":"55"},
	{"date":"15/02/2020","term":"00396","ketqua":["26","36","37","38","42","49","46"],"jackpot":["26","36","37","38","42","49"],"magicnum":"46"},
	{"date":"29/02/2020","term":"00402","ketqua":["09","17","23","26","51","54","32"],"jackpot":["09","17","23","26","51","54"],"magicnum":"32"},
	{"date":"09/07/2020","term":"00448","ketqua":["03","10","11","17","26","54","21"],"jackpot":["03","10","11","17","26","54"],"magicnum":"21"},
	{"date":"30/07/2020","term":"00457","ketqua":["06","07","16","26","29","54","04"],"jackpot":["06","07","16","26","29","54"],"magicnum":"04"},
	{"date":"06/08/2020","term":"00460","ketqua":["02","05","21","24","26","27","11"],"jackpot":["02","05","21","24","26","27"],"magicnum":"11"},
	{"date":"08/08/2020","term":"00461","ketqua":["03","12","24","26","36","43","08"],"jackpot":["03","12","24","26","36","43"],"magicnum":"08"},
	{"date":"22/08/2020","term":"00467","ketqua":["01","20","24","26","35","51","12"],"jackpot":["01","20","24","26","35","51"],"magicnum":"12"},
	{"date":"15/09/2020","term":"00476","ketqua":["13","14","15","17","26","53","21"],"jackpot":["13","14","15","17","26","53"],"magicnum":"21"},
	{"date":"08/10/2020","term":"00486","ketqua":["10","18","20","21","26","51","52"],"jackpot":["10","18","20","21","26","51"],"magicnum":"52"},
	{"date":"02/01/2021","term":"00523","ketqua":["07","19","23","26","35","45","11"],"jackpot":["07","19","23","26","35","45"],"magicnum":"11"},
	{"date":"18/02/2021","term":"00542","ketqua":["02","05","10","22","26","47","53"],"jackpot":["02","05","10","22","26","47"],"magicnum":"53"},
	{"date":"27/03/2021","term":"00558","ketqua":["05","11","17","20","26","37","12"],"jackpot":["05","11","17","20","26","37"],"magicnum":"12"},
	{"date":"27/04/2021","term":"00571","ketqua":["03","09","22","26","32","37","41"],"jackpot":["03","09","22","26","32","37"],"magicnum":"41"},
	{"date":"08/05/2021","term":"00576","ketqua":["14","23","26","37","42","51","40"],"jackpot":["14","23","26","37","42","51"],"magicnum":"40"},
	{"date":"03/06/2021","term":"00587","ketqua":["04","08","21","24","26","47","43"],"jackpot":["04","08","21","24","26","47"],"magicnum":"43"},
	{"date":"20/07/2021","term":"00607","ketqua":["02","08","11","13","17","26","53"],"jackpot":["02","08","11","13","17","26"],"magicnum":"53"},
	{"date":"28/08/2021","term":"00613","ketqua":["10","16","26","27","34","48","51"],"jackpot":["10","16","26","27","34","48"],"magicnum":"51"},
	{"date":"02/09/2021","term":"00615","ketqua":["01","08","12","26","28","45","43"],"jackpot":["01","08","12","26","28","45"],"magicnum":"43"},
	{"date":"23/09/2021","term":"00624","ketqua":["06","07","21","25","27","49","26"],"jackpot":["06","07","21","25","27","49"],"magicnum":"26"},
	{"date":"30/09/2021","term":"00627","ketqua":["18","23","26","32","46","49","54"],"jackpot":["18","23","26","32","46","49"],"magicnum":"54"},
	{"date":"02/10/2021","term":"00628","ketqua":["05","06","22","26","49","51","32"],"jackpot":["05","06","22","26","49","51"],"magicnum":"32"},
	{"date":"23/10/2021","term":"00637","ketqua":["05","11","19","26","28","33","09"],"jackpot":["05","11","19","26","28","33"],"magicnum":"09"},
	{"date":"09/11/2021","term":"00644","ketqua":["12","25","26","47","51","53","16"],"jackpot":["12","25","26","47","51","53"],"magicnum":"16"},
	{"date":"18/12/2021","term":"00661","ketqua":["04","06","19","26","38","41","16"],"jackpot":["04","06","19","26","38","41"],"magicnum":"16"},
	{"date":"11/01/2022","term":"00671","ketqua":["12","25","26","28","33","46","22"],"jackpot":["12","25","26","28","33","46"],"magicnum":"22"},
	{"date":"13/01/2022","term":"00672","ketqua":["07","12","17","26","37","46","28"],"jackpot":["07","12","17","26","37","46"],"magicnum":"28"},
	{"date":"15/01/2022","term":"00673","ketqua":["20","26","41","46","47","48","18"],"jackpot":["20","26","41","46","47","48"],"magicnum":"18"},
	{"date":"27/01/2022","term":"00678","ketqua":["01","26","31","36","40","46","28"],"jackpot":["01","26","31","36","40","46"],"magicnum":"28"},
	{"date":"10/02/2022","term":"00683","ketqua":["03","15","26","35","43","52","07"],"jackpot":["03","15","26","35","43","52"],"magicnum":"07"},
	{"date":"03/03/2022","term":"00692","ketqua":["04","10","16","25","26","43","52"],"jackpot":["04","10","16","25","26","43"],"magicnum":"52"},
	{"date":"12/03/2022","term":"00696","ketqua":["12","16","18","26","30","45","36"],"jackpot":["12","16","18","26","30","45"],"magicnum":"36"},
	{"date":"05/04/2022","term":"00706","ketqua":["05","18","26","36","43","44","45"],"jackpot":["05","18","26","36","43","44"],"magicnum":"45"},
	{"date":"14/06/2022","term":"00736","ketqua":["02","15","26","32","35","36","16"],"jackpot":["02","15","26","32","35","36"],"magicnum":"16"},
	{"date":"02/07/2022","term":"00744","ketqua":["06","26","39","40","46","47","02"],"jackpot":["06","26","39","40","46","47"],"magicnum":"02"},
	{"date":"05/07/2022","term":"00745","ketqua":["05","07","12","26","29","44","38"],"jackpot":["05","07","12","26","29","44"],"magicnum":"38"},
	{"date":"18/08/2022","term":"00764","ketqua":["23","27","31","37","38","42","26"],"jackpot":["23","27","31","37","38","42"],"magicnum":"26"},
	{"date":"22/09/2022","term":"00779","ketqua":["12","14","19","29","44","47","26"],"jackpot":["12","14","19","29","44","47"],"magicnum":"26"},
	{"date":"11/10/2022","term":"00787","ketqua":["11","26","34","40","46","52","01"],"jackpot":["11","26","34","40","46","52"],"magicnum":"01"},
	{"date":"15/11/2022","term":"00802","ketqua":["04","20","26","36","47","51","33"],"jackpot":["04","20","26","36","47","51"],"magicnum":"33"},
	{"date":"22/11/2022","term":"00805","ketqua":["03","09","21","22","26","35","15"],"jackpot":["03","09","21","22","26","35"],"magicnum":"15"},
	{"date":"22/12/2022","term":"00818","ketqua":["14","26","35","43","45","48","03"],"jackpot":["14","26","35","43","45","48"],"magicnum":"03"},
	{"date":"14/01/2023","term":"00828","ketqua":["05","17","24","30","43","53","26"],"jackpot":["05","17","24","30","43","53"],"magicnum":"26"},
	{"date":"18/02/2023","term":"00842","ketqua":["11","23","26","29","43","50","05"],"jackpot":["11","23","26","29","43","50"],"magicnum":"05"},
	{"date":"13/04/2023","term":"00865","ketqua":["22","26","28","37","39","48","15"],"jackpot":["22","26","28","37","39","48"],"magicnum":"15"},
	{"date":"23/05/2023","term":"00882","ketqua":["26","27","35","36","47","54","40"],"jackpot":["26","27","35","36","47","54"],"magicnum":"40"},
	{"date":"20/06/2023","term":"00894","ketqua":["07","23","26","31","35","53","32"],"jackpot":["07","23","26","31","35","53"],"magicnum":"32"},
	{"date":"20/07/2023","term":"00907","ketqua":["05","34","36","38","47","50","26"],"jackpot":["05","34","36","38","47","50"],"magicnum":"26"},
	{"date":"29/07/2023","term":"00911","ketqua":["16","23","25","26","29","40","32"],"jackpot":["16","23","25","26","29","40"],"magicnum":"32"},
	{"date":"12/09/2023","term":"00930","ketqua":["26","31","32","39","45","55","28"],"jackpot":["26","31","32","39","45","55"],"magicnum":"28"},
	{"date":"21/09/2023","term":"00934","ketqua":["16","26","33","34","41","43","53"],"jackpot":["16","26","33","34","41","43"],"magicnum":"53"},
	{"date":"10/10/2023","term":"00942","ketqua":["06","23","26","37","44","46","33"],"jackpot":["06","23","26","37","44","46"],"magicnum":"33"},
	{"date":"24/10/2023","term":"00948","ketqua":["12","20","26","33","40","44","24"],"jackpot":["12","20","26","33","40","44"],"magicnum":"24"},
	{"date":"02/11/2023","term":"00952","ketqua":["09","15","17","21","26","36","13"],"jackpot":["09","15","17","21","26","36"],"magicnum":"13"},
	{"date":"23/11/2023","term":"00961","ketqua":["04","06","26","33","52","55","15"],"jackpot":["04","06","26","33","52","55"],"magicnum":"15"},
	{"date":"09/12/2023","term":"00968","ketqua":["06","09","26","27","34","47","41"],"jackpot":["06","09","26","27","34","47"],"magicnum":"41"},
	{"date":"16/12/2023","term":"00971","ketqua":["13","15","21","26","34","35","45"],"jackpot":["13","15","21","26","34","35"],"magicnum":"45"},
	{"date":"03/02/2024","term":"00992","ketqua":["04","06","07","13","18","26","49"],"jackpot":["04","06","07","13","18","26"],"magicnum":"49"},
	{"date":"15/02/2024","term":"00996","ketqua":["03","07","08","18","21","26","19"],"jackpot":["03","07","08","18","21","26"],"magicnum":"19"},
	{"date":"24/02/2024","term":"01000","ketqua":["01","03","22","27","38","40","26"],"jackpot":["01","03","22","27","38","40"],"magicnum":"26"},
	{"date":"14/03/2024","term":"01008","ketqua":["21","25","26","29","41","51","39"],"jackpot":["21","25","26","29","41","51"],"magicnum":"39"},
	{"date":"19/03/2024","term":"01010","ketqua":["06","25","39","45","46","55","26"],"jackpot":["06","25","39","45","46","55"],"magicnum":"26"},
	{"date":"28/03/2024","term":"01014","ketqua":["01","07","18","26","38","49","21"],"jackpot":["01","07","18","26","38","49"],"magicnum":"21"},
	{"date":"30/04/2024","term":"01028","ketqua":["13","16","26","46","49","54","08"],"jackpot":["13","16","26","46","49","54"],"magicnum":"08"},
	{"date":"07/05/2024","term":"01031","ketqua":["21","26","35","41","44","52","13"],"jackpot":["21","26","35","41","44","52"],"magicnum":"13"},
	{"date":"06/06/2024","term":"01044","ketqua":["18","26","38","39","47","51","55"],"jackpot":["18","26","38","39","47","51"],"magicnum":"55"},
	{"date":"15/06/2024","term":"01048","ketqua":["05","10","14","20","26","51","36"],"jackpot":["05","10","14","20","26","51"],"magicnum":"36"}
]